type_dep/__init__.py
type_dep/_core.py
type_dep-0.0.2.dist-info/LICENSE
type_dep-0.0.2.dist-info/METADATA
type_dep-0.0.2.dist-info/WHEEL
type_dep-0.0.2.dist-info/top_level.txt
type_dep-0.0.2.dist-info/RECORD
