Metadata-Version: 2.1
Name: type-dep
Version: 0.0.2
Summary: type_dep is a dependency injection framework that uses type hints to inject dependencies (much like Angular, Dotnet and the like)
Home-page: https://github.com/sopherapps/type_dep
Author: Martin Ahindura
Author-email: team.sopherapps@gmail.com
License: MIT
Platform: UNKNOWN
Classifier: License :: OSI Approved :: MIT License
Classifier: Programming Language :: Python :: 3
Classifier: Programming Language :: Python :: 3.7
License-File: LICENSE
